kasr/__init__.py
kasr-0.1.dist-info/METADATA
kasr-0.1.dist-info/WHEEL
kasr-0.1.dist-info/top_level.txt
kasr-0.1.dist-info/RECORD
