Metadata-Version: 2.4
Name: kasr
Version: 0.1
Summary: کتابخانه ساده عملیات کسر
Author: sama
Author-email: bagherisama78@gmail.com
Dynamic: author
Dynamic: author-email
Dynamic: summary
